CONTRIBUTING.md
LICENSE
MANIFEST.in
README.md
VERSION
manage.py
setup.py
./api/__init__.py
./api/middleware.py
./api/urls.py
./api/serializers/__init__.py
./api/serializers/sync.py
./api/views/__init__.py
./api/views/root.py
./api/views/sync.py
./apps/__init__.py
./apps/address/__init__.py
./apps/address/admin.py
./apps/address/apps.py
./apps/address/forms.py
./apps/address/models.py
./apps/address/management/__init__.py
./apps/address/management/commands/__init__.py
./apps/address/management/commands/import_addresses.py
./apps/address/migrations/0001_initial.py
./apps/address/migrations/0002_auto_20150927_1547.py
./apps/address/migrations/0003_auto_20150927_1551.py
./apps/address/migrations/0004_auto_20170226_1122.py
./apps/address/migrations/0005_regenerate_user_address_hashes.py
./apps/address/migrations/0006_auto_20181115_1953.py
./apps/address/migrations/0007_useraddress_floor_number.py
./apps/address/migrations/0008_useraddress_company.py
./apps/address/migrations/0009_bankaccount.py
./apps/address/migrations/0010_auto_20210104_1041.py
./apps/address/migrations/0011_bankaccount_deleted.py
./apps/address/migrations/0012_auto_20210104_1208.py
./apps/address/migrations/0013_auto_20210105_1118.py
./apps/address/migrations/0014_auto_20210105_1148.py
./apps/address/migrations/0015_auto_20210107_0930.py
./apps/address/migrations/0016_auto_20210114_1545.py
./apps/address/migrations/0017_auto_20210202_1725.py
./apps/address/migrations/0018_useraddress_sage_id.py
./apps/address/migrations/0019_useraddress_is_company.py
./apps/address/migrations/0020_useraddress_cost_center.py
./apps/address/migrations/0021_auto_20210216_1256.py
./apps/address/migrations/0022_auto_20210224_1514.py
./apps/address/migrations/0023_auto_20210425_1819.py
./apps/address/migrations/0024_auto_20210605_1943.py
./apps/address/migrations/0025_auto_20210609_1033.py
./apps/address/migrations/__init__.py
./apps/basket/__init__.py
./apps/basket/admin.py
./apps/basket/apps.py
./apps/basket/forms.py
snake_shop.egg-info/PKG-INFO
snake_shop.egg-info/SOURCES.txt
snake_shop.egg-info/dependency_links.txt
snake_shop.egg-info/requires.txt
snake_shop.egg-info/top_level.txt
